MANIFEST.in
README.txt
setup.py
XOPPY.egg-info/PKG-INFO
XOPPY.egg-info/SOURCES.txt
XOPPY.egg-info/dependency_links.txt
XOPPY.egg-info/entry_points.txt
XOPPY.egg-info/namespace_packages.txt
XOPPY.egg-info/not-zip-safe
XOPPY.egg-info/requires.txt
XOPPY.egg-info/top_level.txt
orangecontrib/__init__.py
orangecontrib/xoppy/__init__.py
orangecontrib/xoppy/bin.darwin/bfield
orangecontrib/xoppy/bin.darwin/bfield2
orangecontrib/xoppy/bin.darwin/compliance
orangecontrib/xoppy/bin.darwin/cryst_ml
orangecontrib/xoppy/bin.darwin/cryst_pp
orangecontrib/xoppy/bin.darwin/cryst_tt
orangecontrib/xoppy/bin.darwin/cryst_za
orangecontrib/xoppy/bin.darwin/diff_pat
orangecontrib/xoppy/bin.darwin/inpro
orangecontrib/xoppy/bin.darwin/mlayer
orangecontrib/xoppy/bin.darwin/ndiff_pat
orangecontrib/xoppy/bin.darwin/tasmip
orangecontrib/xoppy/bin.darwin/tc
orangecontrib/xoppy/bin.darwin/txt2u
orangecontrib/xoppy/bin.darwin/u2txt
orangecontrib/xoppy/bin.darwin/urgent
orangecontrib/xoppy/bin.darwin/us
orangecontrib/xoppy/bin.darwin/ws
orangecontrib/xoppy/bin.darwin/xcom
orangecontrib/xoppy/bin.darwin/xpowder_fml
orangecontrib/xoppy/bin.darwin/xtubes
orangecontrib/xoppy/bin.darwin/yaup
orangecontrib/xoppy/bin.linux/bfield
orangecontrib/xoppy/bin.linux/bfield2
orangecontrib/xoppy/bin.linux/compliance
orangecontrib/xoppy/bin.linux/cryst_ml
orangecontrib/xoppy/bin.linux/cryst_pp
orangecontrib/xoppy/bin.linux/cryst_tt
orangecontrib/xoppy/bin.linux/cryst_za
orangecontrib/xoppy/bin.linux/diff_pat
orangecontrib/xoppy/bin.linux/inpro
orangecontrib/xoppy/bin.linux/mlayer
orangecontrib/xoppy/bin.linux/ndiff_pat
orangecontrib/xoppy/bin.linux/tasmip
orangecontrib/xoppy/bin.linux/tc
orangecontrib/xoppy/bin.linux/txt2u
orangecontrib/xoppy/bin.linux/u2txt
orangecontrib/xoppy/bin.linux/urgent
orangecontrib/xoppy/bin.linux/us
orangecontrib/xoppy/bin.linux/ws
orangecontrib/xoppy/bin.linux/xcom
orangecontrib/xoppy/bin.linux/xpowder_fml
orangecontrib/xoppy/bin.linux/xtubes
orangecontrib/xoppy/bin.linux/yaup
orangecontrib/xoppy/doc_txt/bfield.txt
orangecontrib/xoppy/doc_txt/black_body.txt
orangecontrib/xoppy/doc_txt/black_body_par.txt
orangecontrib/xoppy/doc_txt/bm.txt
orangecontrib/xoppy/doc_txt/bm_par.txt
orangecontrib/xoppy/doc_txt/crl.txt
