Metadata-Version: 1.1
Name: XOPPY
Version: 1.0.0
Summary: XOPPY: XOP (X-ray oriented programs) in Python
Home-page: https://github.com/srio/Orange-XOPPY
Author: Manuel Sanchez del Rio, Luca Rebuffi, and Bioinformatics Laboratory, FRI UL
Author-email: srio@esrf.eu
License: GPLv3
Download-URL: https://github.com/srio/Orange-XOPPY
Keywords: X-ray optics,simulator,oasys
Platform: UNKNOWN
Classifier: Development Status :: 4 - Beta
Classifier: Environment :: X11 Applications :: Qt
Classifier: Environment :: Console
Classifier: Environment :: Plugins
Classifier: Programming Language :: Python :: 3
Classifier: Intended Audience :: Science/Research
